{
  "name": "Isabel Carson",
  "age": 29,
  "address": {
    "street": "Casba Street",
    "city": "Semrodpi",
    "state": "MD",
    "zip": "34516"
  },
  "contact": {
    "phone": "(676) 952-1320",
    "servicePhone": "800258775"
  },
  "birthday": "1977-03-13T18:35:06.272Z",
  "ip": "28.190.89.202",
  "foo": "bar",
  "profile": {
    "about": "Iz do kurum tozocwe tu cebgiwa isajuwa nuuluti hezugim zegvuroc pevopoc cadtap. Ema wiwvisi pono fehennug ikubu ti sohehfuh awo ut mina nakeahu sumwucpu doirogo nitaadu ogufumob vav eflu. Cu nebanid naf pitcidavo gos duh fel ozoneztos po car jopapala bog icepeh lamsuco koklav kicti riw joseepa. Cav zocawi kujhos wuvcu zahga kipuhwac zosupesos vidi fikez kupkosi vuvma tergapu obe ab.",
    "bio": "Po hudaeji vavkuni uhbinmum kocige lebokdo piscu tubijeb sogkora ga guavka viobusud udozifviz effos zopgepsi kebanu. Jozu osejagsaf ma usakolsom bepetlat alpur da isokoika betot if ten sawid bu wa siar taacociw bismuc. Muemo cotbugus jugitek zegzajke zoowop mabuvi gid viz lose beh ko kachepon il zugvi zij ercife abgi lenutvuw. Mo hu jofnoz tu op doklap olaj si diwteh etna kin hawzi epufe eno vi gescoc uhkured rizuwsi."
  },
  "apiKey": "0da75454d1a0f0d1ffd8e1c7e53a7af2635f724e2b6d5ac487095086333f6f9c",
  "currency": {
    "code": "TTD",
    "name": "Trinidad and Tobago Dollar"
  }
}