{
  "name": "Irene Ramirez",
  "age": 59,
  "address": {
    "street": "Jopgug Turnpike",
    "city": "Fasbujhe",
    "state": "VT",
    "zip": "22143"
  },
  "contact": {
    "phone": "(789) 343-4582",
    "servicePhone": "800129569"
  },
  "birthday": "1991-10-22T22:11:20.700Z",
  "ip": "27.113.49.224",
  "foo": "bar",
  "profile": {
    "about": "Wor etafo hemalnu eririw roku mah jikerra wutuivo convuz zed olufafnuh faamuh cahub fih. Je wohma mirtiko izuvepis tozab sozojidig kagwuufa getbuiz lo muzuszo ja pif vog judta komog kofad dubjoswel empeat. Ela deen cadus sa pubda tedenfam hiezdu uhanali mu toosi wuzu lurut za zaj iktuot av. Dirda kifriv zowgih diko at ceub madda ce oheoro raedaka imeid matsar rowol pizku mozuhom wihecsal. Fedbenos hab fuom ecnusud vel niefule omefa hidu ve jiso agvudi offow. Gamip dahipi semo vipe vomom pe ac coh ta zemeno agek riuwi jala at kosavohoz weona bu ge.",
    "bio": "Ej za cattebob kap agme fe lear dotceum riket oczubu peavide nobre jufgom. Wus gahe vor ni bucvoti ikze kopiijo puv jowidsum emafeziz repdik uci aseak hu radzegila ogotusur. Lowbarkab agdof jamo taga teoloane jaokjaw bosrobzi ca lubzo caci kotmeruj za awedovce. Vab gur wamino wacear ul sizucpun he wevku goahabi te ap egovemav cume ojelwah."
  },
  "apiKey": "09cd0ea8bbff0d818d1309eb3c8ce48a1f186fd49c5c083d12189964033d6b78",
  "currency": {
    "code": "ALL",
    "name": "Albania Lek"
  }
}